physicsexp/__init__.py
physicsexp/autophy.py
physicsexp/ftpup.py
physicsexp/gendocx.py
physicsexp/mainfunc.py
physicsexp-0.0.3.dist-info/LICENSE
physicsexp-0.0.3.dist-info/METADATA
physicsexp-0.0.3.dist-info/WHEEL
physicsexp-0.0.3.dist-info/top_level.txt
physicsexp-0.0.3.dist-info/RECORD
