Metadata-Version: 2.1
Name: physicsexp
Version: 0.0.3
Summary: A simple wrapper of numpy and matplotlib to make physics experiment data analyse easier
Home-page: https://github.com/ustcpetergu/PhysicsExp
Author: ustcpetergu
Author-email: guyimin@mail.ustc.edu.cn
License: UNKNOWN
Platform: UNKNOWN
Classifier: Programming Language :: Python :: 3
Classifier: License :: OSI Approved :: MIT License
Classifier: Operating System :: OS Independent
Requires-Dist: numpy
Requires-Dist: matplotlib
Requires-Dist: scipy
Requires-Dist: python-docx
